{
  "name": "Profile",
  "plural": "profiles",
  "base": "PersistedModel",
  "idInjection": true,
  "options": {
    "validateUpsert": true
  },
  "properties": {
    "username": {
      "type": "string",
      "required": true
    },
    "accountName": {
      "type": "string"
    },
    "characterName": {
      "type": "string"
    },
    "characterLevel": {
      "type": "string"
    },
    "characterClass": {
      "type": "string"
    },
    "realm": {
      "type": "string"
    },
    "timeZone": {
      "type": "string"
    },
    "hoursAvailable": {
      "type": "string"
    }

  },
  "validations": [],
  "relations": {},
  "acls": [],
  "methods": {}
}
